{"cameraMode":{"drawMode":0,"name":"Shaded","section":"Shading Mode"},"sceneLighting":true,"audioPlay":false,"sceneViewState":{"m_AlwaysRefresh":false,"showFog":true,"showSkybox":true,"showFlares":true,"showImageEffects":true,"showParticleSystems":true,"showVisualEffectGraphs":true,"m_FxEnabled":true},"in2DMode":false,"pivot":{"x":80.82112884521485,"y":6.501957893371582,"z":-13.804057121276856},"rotation":{"x":-0.14288733899593354,"y":-0.745346188545227,"z":0.16387492418289185,"w":-0.6312317252159119},"size":130.78831481933595,"orthographic":false}